inline/__init__.py
inline/inlinegpt.py
InlineGPT-0.1.0.dist-info/METADATA
InlineGPT-0.1.0.dist-info/WHEEL
InlineGPT-0.1.0.dist-info/top_level.txt
InlineGPT-0.1.0.dist-info/RECORD
