Metadata-Version: 2.1
Name: InlineGPT
Version: 0.1.0
Summary: A Python package designed to provide direct inline support for developers. It integrates GPT (Generative Pre-trained Transformer) functionality directly into Python applications, enabling developers to handle errors effectively by suggesting appropriate changes.
Home-page: https://github.com/rahulaauji-30/InlineGPT.git
Author: Rahul Parihar
Author-email: rahulaauji71@gmail.com
Project-URL: Bug Reports, https://github.com/rahulaauji-30/InlineGPT/issues
Project-URL: Source, https://github.com/rahulaauji-30/InlineGPT
Classifier: Development Status :: 3 - Alpha
Classifier: Intended Audience :: Developers
Classifier: License :: OSI Approved :: MIT License
Classifier: Programming Language :: Python :: 3
Classifier: Programming Language :: Python :: 3.6
Classifier: Programming Language :: Python :: 3.7
Classifier: Programming Language :: Python :: 3.8
Classifier: Programming Language :: Python :: 3.9
Classifier: Programming Language :: Python :: 3.10
Classifier: Operating System :: OS Independent
Requires-Python: >=3.6
Requires-Dist: google-generativeai >=0.7.2
